metainer/__init__.py
metainer/core.py
metainer/mixin.py
metainer-0.2.dist-info/LICENSE
metainer-0.2.dist-info/METADATA
metainer-0.2.dist-info/WHEEL
metainer-0.2.dist-info/top_level.txt
metainer-0.2.dist-info/RECORD
